{
  "nodes": [
    {
      "id": "style-minimalist",
      "label": "Style Minimalist",
      "formula_type": null,
      "formula_args": []
    },
    {
      "id": "high-readability",
      "label": "High Readability",
      "formula_type": null,
      "formula_args": []
    },
    {
      "id": "uses-superlative-forms",
      "label": "Uses Superlative Forms",
      "formula_type": null,
      "formula_args": []
    },
    {
      "id": "theme-growth",
      "label": "Theme Growth",
      "formula_type": null,
      "formula_args": []
    },
    {
      "id": "topic-time-travel",
      "label": "Topic Time Travel",
      "formula_type": null,
      "formula_args": []
    },
    {
      "id": "topic-hidden-treasures",
      "label": "Topic Hidden Treasures",
      "formula_type": null,
      "formula_args": []
    },
    {
      "id": "clear-concise",
      "label": "Clear Concise",
      "formula_type": "And",
      "formula_args": [
        "style-minimalist",
        "high-readability"
      ]
    },
    {
      "id": "emphatic",
      "label": "Emphatic",
      "formula_type": "And",
      "formula_args": [
        "uses-superlative-forms",
        {
          "formula_type": "Not",
          "formula_args": [
            "style-minimalist"
          ]
        }
      ]
    },
    {
      "id": "thematic-arc",
      "label": "Thematic Arc",
      "formula_type": "And",
      "formula_args": [
        "theme-growth",
        {
          "formula_type": "Or",
          "formula_args": [
            "topic-time-travel",
            "topic-hidden-treasures"
          ]
        }
      ]
    },
    {
      "id": "compelling",
      "label": "Compelling",
      "formula_type": "And",
      "formula_args": [
        "clear-concise",
        {
          "formula_type": "Or",
          "formula_args": [
            "emphatic",
            "thematic-arc"
          ]
        }
      ]
    }
  ],
  "edges": [
    {
      "source": "style-minimalist",
      "target": "clear-concise"
    },
    {
      "source": "high-readability",
      "target": "clear-concise"
    },
    {
      "source": "uses-superlative-forms",
      "target": "emphatic"
    },
    {
      "source": "style-minimalist",
      "target": "emphatic"
    },
    {
      "source": "theme-growth",
      "target": "thematic-arc"
    },
    {
      "source": "topic-time-travel",
      "target": "thematic-arc"
    },
    {
      "source": "topic-hidden-treasures",
      "target": "thematic-arc"
    },
    {
      "source": "clear-concise",
      "target": "compelling"
    },
    {
      "source": "emphatic",
      "target": "compelling"
    },
    {
      "source": "thematic-arc",
      "target": "compelling"
    }
  ]
}